CHANGES.txt
CONTRIBUTORS.txt
README.txt
setup.cfg
setup.py
docs/HISTORY.txt
docs/INSTALL.txt
docs/LICENSE.EUPL
docs/LICENSE.GPL
docs/LICENSE.txt
slc/__init__.py
slc.editonpro.egg-info/PKG-INFO
slc.editonpro.egg-info/SOURCES.txt
slc.editonpro.egg-info/dependency_links.txt
slc.editonpro.egg-info/entry_points.txt
slc.editonpro.egg-info/namespace_packages.txt
slc.editonpro.egg-info/not-zip-safe
slc.editonpro.egg-info/paster_plugins.txt
slc.editonpro.egg-info/requires.txt
slc.editonpro.egg-info/top_level.txt
slc/editonpro/README.txt
slc/editonpro/__init__.py
slc/editonpro/configure.zcml
slc/editonpro/profiles.zcml
slc/editonpro/setuphandlers.py
slc/editonpro/skins.zcml
slc/editonpro/tests.py
slc/editonpro/version.txt
slc/editonpro/profiles/default/import_steps.xml
slc/editonpro/profiles/default/jsregistry.xml
slc/editonpro/profiles/default/skins.xml
slc/editonpro/profiles/default/slc.editonpro_various.txt
slc/editonpro/skins/editonpro/editonpro.js.dtml
slc/editonpro/skins/editonpro/editonpro_wysiwyg_support.pt