Metadata-Version: 1.0
Name: slc.editonpro
Version: 1.2-r250095
Summary: Integration layer for Edit On Pro Webeditor
Home-page: https://svn.plone.org/svn/collective/slc.editonpro
Author: Syslabcom GmbH
Author-email: info@syslab.com
License: GPL + EUPL
Keywords: plone wysiwyg editor editonpro
Platform: UNKNOWN
Classifier: Framework :: Plone
Classifier: Framework :: Zope2
Classifier: Framework :: Zope3
Classifier: Programming Language :: Python
Classifier: Topic :: Software Development :: Libraries :: Python Modules
Classifier: License :: OSI Approved :: GNU General Public License (GPL)
Classifier: License :: OSI Approved :: European Union Public Licence 1.1 (EUPL 1.1)
